README.md
setup.py
outlook_oauth2/__init__.py
outlook_oauth2.egg-info/PKG-INFO
outlook_oauth2.egg-info/SOURCES.txt
outlook_oauth2.egg-info/dependency_links.txt
outlook_oauth2.egg-info/requires.txt
outlook_oauth2.egg-info/top_level.txt
outlook_oauth2/core/__init__.py
outlook_oauth2/core/attachment.py
outlook_oauth2/core/contact.py
outlook_oauth2/core/folder.py
outlook_oauth2/core/mailbox.py
outlook_oauth2/core/main.py
outlook_oauth2/core/message.py
outlook_oauth2/internal/__init__.py
outlook_oauth2/internal/errors.py
outlook_oauth2/internal/utils.py